{
  "id": 325,
  "slug": "video-engagement-metrics-ai-overviews",
  "title": "Video Engagement Metrics: The Hidden Signal for AI Overviews",
  "excerpt": "AI overviews rely heavily on user satisfaction signals. Learn why metrics like audience retention and watch time are critical for your AEO success.",
  "author": "Corey Spicer",
  "date": "2026-03-25",
  "category": "seo",
  "readTime": "10 min read",
  "image": "https://images.unsplash.com/photo-1611162617474-5b21e879e113?w=800&h=400&fit=crop",
  "tags": [
    "Video Analytics",
    "Engagement Metrics",
    "AI Overviews",
    "Retention"
  ],
  "content": "<p>Answer Engines are designed to provide the *best* answer, not just the most relevant one. How do they know an answer is the best? User engagement.</p><h2>Retention is King</h2><p>If users consistently drop off 10 seconds into your video, AI algorithms assume the content is unhelpful. Maximize retention by removing fluff, keeping visuals dynamic, and delivering the core value (the answer!) as quickly as possible. High retention leads to frequent AI citations.</p>"
}